device/__init__.py
device/device.py
dnac/__init__.py
dnac/dnac.py
ezdnac/__init__.py
ezdnac/cli.py
ezdnac/excepts.py
ezdnac/utils.py
ezdnac/device/__init__.py
ezdnac/device/device.py
ezdnac/dnac/__init__.py
ezdnac/dnac/dnac.py
ezdnac/template/__init__.py
ezdnac/template/template.py
template/__init__.py
template/template.py
ezdnac-0.0.56.dist-info/METADATA
ezdnac-0.0.56.dist-info/WHEEL
ezdnac-0.0.56.dist-info/top_level.txt
ezdnac-0.0.56.dist-info/RECORD
